setup.py
vida/__init__.py
vida/vida.py
vida.egg-info/PKG-INFO
vida.egg-info/SOURCES.txt
vida.egg-info/dependency_links.txt
vida.egg-info/requires.txt
vida.egg-info/top_level.txt