Metadata-Version: 1.1
Name: vida
Version: 0.3
Summary: Python binding for Vida data visualizations
Home-page: https://github.com/vidalab/pyvida
Author: Phuoc Do
Author-email: phuocd@vida.io
License: UNKNOWN
Download-URL: https://github.com/vidalab/pyvida/archive/0.1.tar.gz
Platform: UNKNOWN
Classifier: Intended Audience :: Developers
Classifier: License :: OSI Approved :: BSD License
Classifier: Operating System :: OS Independent
Classifier: Topic :: Software Development
